<annotation>
	<folder>bird-image</folder>
	<filename>104.jpg</filename>
	<path>D:\bird-image\104.jpg</path>
	<source>
		<database>Unknown</database>
	</source>
	<size>
		<width>500</width>
		<height>375</height>
		<depth>3</depth>
	</size>
	<segmented>0</segmented>
	<object>
		<name>bird-nest</name>
		<pose>Unspecified</pose>
		<truncated>0</truncated>
		<difficult>0</difficult>
		<bndbox>
			<xmin>160</xmin>
			<ymin>187</ymin>
			<xmax>260</xmax>
			<ymax>246</ymax>
		</bndbox>
	</object>
</annotation>
